{
	"animations": [
		{
			"offsets": [
				12,
				-6
			],
			"loop": true,
			"fps": 24,
			"anim": "idle-loop",
			"indices": [
				10,
				11,
				12,
				12
			],
			"name": "Dad idle dance"
		},
		{
			"offsets": [
				-9,
				10
			],
			"loop": true,
			"fps": 24,
			"anim": "singLEFT-loop",
			"indices": [
				12,
				13,
				14,
				15
			],
			"name": "Dad Sing Note LEFT"
		},
		{
			"offsets": [
				0,
				27
			],
			"loop": true,
			"fps": 24,
			"anim": "singRIGHT-loop",
			"indices": [
				15,
				16,
				17,
				18
			],
			"name": "Dad Sing Note RIGHT"
		},
		{
			"offsets": [
				-6,
				50
			],
			"loop": true,
			"fps": 24,
			"anim": "singUP-loop",
			"indices": [
				56,
				57,
				58,
				59
			],
			"name": "Dad Sing Note UP"
		},
		{
			"offsets": [
				-40,
				-30
			],
			"loop": false,
			"fps": 24,
			"anim": "singDOWN-alt",
			"indices": [],
			"name": "NewPhase2Sonic Laugh"
		},
		{
			"offsets": [
				244,
				-281
			],
			"loop": false,
			"fps": 24,
			"anim": "singLEFT",
			"indices": [],
			"name": "SonicBf NOTE LEFT"
		},
		{
			"offsets": [
				232,
				-278
			],
			"loop": false,
			"fps": 24,
			"anim": "singUP",
			"indices": [],
			"name": "SonicBf NOTE UP"
		},
		{
			"offsets": [
				200,
				-310
			],
			"loop": false,
			"fps": 24,
			"anim": "singDOWN",
			"indices": [],
			"name": "SonicBf NOTE DOWN"
		},
		{
			"offsets": [
				270,
				-283
			],
			"loop": false,
			"fps": 24,
			"anim": "singRIGHT",
			"indices": [],
			"name": "SonicBf NOTE RIGHT"
		},
		{
			"offsets": [
				223,
				-288
			],
			"loop": false,
			"fps": 24,
			"anim": "idle",
			"indices": [],
			"name": "SonicBf idle dance"
		}
	],
	"no_antialiasing": false,
	"image": "characters/SonicWBfFate",
	"position": [
		290,
		0
	],
	"healthicon": "Sonic",
	"flip_x": false,
	"healthbar_colors": [
		0,
		107,
		255
	],
	"camera_position": [
		-350,
		270
	],
	"sing_duration": 6.1,
	"scale": 1
}